testjbednarczyk/__init__.py
testjbednarczyk/m_mod_jbednarczyk.py
testjbednarczyk-0.0.1.dist-info/METADATA
testjbednarczyk-0.0.1.dist-info/WHEEL
testjbednarczyk-0.0.1.dist-info/top_level.txt
testjbednarczyk-0.0.1.dist-info/RECORD
