Metadata-Version: 2.1
Name: testjbednarczyk
Version: 0.0.1
Summary: My test package
Author-email: AZ <test@test.pl>
License: MIT License
Keywords: testjbednarczyk,name,surname,fun fuction
Classifier: Natural Language :: Polish
Classifier: Framework :: IDLE
Requires-Python: >=3.0
Requires-Dist: python-version (>=3.0)
Requires-Dist: numpy
